<annotation>
	<folder>Horse</folder>
	<filename>10ee0f7777272371.jpg</filename>
	<path>C:\Users\Partenaire\Desktop\dowloader\downloader\images\train\Horse\10ee0f7777272371.jpg</path>
	<source>
		<database>Unknown</database>
	</source>
	<size>
		<width>640</width>
		<height>480</height>
		<depth>3</depth>
	</size>
	<segmented>0</segmented>
	<object>
		<name>horse</name>
		<pose>Unspecified</pose>
		<truncated>0</truncated>
		<difficult>0</difficult>
		<bndbox>
			<xmin>119</xmin>
			<ymin>50</ymin>
			<xmax>615</xmax>
			<ymax>443</ymax>
		</bndbox>
	</object>
</annotation>
