<annotation>
	<folder>Kangaroo</folder>
	<filename>16bfd12248597b62.jpg</filename>
	<path>C:\Users\Partenaire\Desktop\dowloader\downloader\images\train\Kangaroo\16bfd12248597b62.jpg</path>
	<source>
		<database>Unknown</database>
	</source>
	<size>
		<width>640</width>
		<height>480</height>
		<depth>3</depth>
	</size>
	<segmented>0</segmented>
	<object>
		<name>kangaroo</name>
		<pose>Unspecified</pose>
		<truncated>0</truncated>
		<difficult>0</difficult>
		<bndbox>
			<xmin>148</xmin>
			<ymin>114</ymin>
			<xmax>369</xmax>
			<ymax>348</ymax>
		</bndbox>
	</object>
	<object>
		<name>kangaroo</name>
		<pose>Unspecified</pose>
		<truncated>1</truncated>
		<difficult>0</difficult>
		<bndbox>
			<xmin>408</xmin>
			<ymin>211</ymin>
			<xmax>640</xmax>
			<ymax>383</ymax>
		</bndbox>
	</object>
</annotation>
