<annotation>
	<folder>Tiger</folder>
	<filename>1e93abe61d6b5e14.jpg</filename>
	<path>C:\Users\Partenaire\Desktop\dowloader\downloader\images\train\Tiger\1e93abe61d6b5e14.jpg</path>
	<source>
		<database>Unknown</database>
	</source>
	<size>
		<width>640</width>
		<height>480</height>
		<depth>3</depth>
	</size>
	<segmented>0</segmented>
	<object>
		<name>tiger</name>
		<pose>Unspecified</pose>
		<truncated>0</truncated>
		<difficult>0</difficult>
		<bndbox>
			<xmin>164</xmin>
			<ymin>93</ymin>
			<xmax>614</xmax>
			<ymax>351</ymax>
		</bndbox>
	</object>
</annotation>
