<annotation>
	<folder>train</folder>
	<filename>236.jpg</filename>
	<path>C:\Users\tobia\OneDrive\Documents\GitHub\object_detection_demo\data\images\train\236.jpg</path>
	<source>
		<database>Unknown</database>
	</source>
	<size>
		<width>800</width>
		<height>600</height>
		<depth>3</depth>
	</size>
	<segmented>0</segmented>
	<object>
		<name>queen</name>
		<pose>Unspecified</pose>
		<truncated>0</truncated>
		<difficult>0</difficult>
		<bndbox>
			<xmin>108</xmin>
			<ymin>117</ymin>
			<xmax>499</xmax>
			<ymax>410</ymax>
		</bndbox>
	</object>
	<object>
		<name>king</name>
		<pose>Unspecified</pose>
		<truncated>0</truncated>
		<difficult>0</difficult>
		<bndbox>
			<xmin>431</xmin>
			<ymin>122</ymin>
			<xmax>767</xmax>
			<ymax>393</ymax>
		</bndbox>
	</object>
</annotation>
