<annotation>
	<folder>cabildo_buenos_aires_800</folder>
	<filename>108.jpg</filename>
	<path>C:\Users\bfresco\Desktop\cabildo\images\cabildo_buenos_aires_800\108.jpg</path>
	<source>
		<database>Unknown</database>
	</source>
	<size>
		<width>800</width>
		<height>600</height>
		<depth>3</depth>
	</size>
	<segmented>0</segmented>
	<object>
		<name>cabildo</name>
		<pose>Unspecified</pose>
		<truncated>0</truncated>
		<difficult>0</difficult>
		<bndbox>
			<xmin>117</xmin>
			<ymin>31</ymin>
			<xmax>677</xmax>
			<ymax>579</ymax>
		</bndbox>
	</object>
</annotation>
