<annotation>
	<folder>Cat</folder>
	<filename>315d1413ae03e219.jpg</filename>
	<path>C:\Users\Partenaire\Desktop\dowloader\downloader\images\train\Cat\315d1413ae03e219.jpg</path>
	<source>
		<database>Unknown</database>
	</source>
	<size>
		<width>640</width>
		<height>480</height>
		<depth>3</depth>
	</size>
	<segmented>0</segmented>
	<object>
		<name>cat</name>
		<pose>Unspecified</pose>
		<truncated>1</truncated>
		<difficult>0</difficult>
		<bndbox>
			<xmin>295</xmin>
			<ymin>45</ymin>
			<xmax>640</xmax>
			<ymax>424</ymax>
		</bndbox>
	</object>
</annotation>
