<annotation>
	<folder>images</folder>
	<filename>uav6.jpg</filename>
	<path>/home/santhui/PythonProject/My_Project/duplicate_images_remove/dataset/uav/uav/images/uav6.jpg</path>
	<source>
		<database>Unknown</database>
	</source>
	<size>
		<width>500</width>
		<height>500</height>
		<depth>3</depth>
	</size>
	<segmented>0</segmented>
	<object>
		<name>uav6</name>
		<pose>Unspecified</pose>
		<truncated>0</truncated>
		<difficult>0</difficult>
		<bndbox>
			<xmin>136</xmin>
			<ymin>352</ymin>
			<xmax>244</xmax>
			<ymax>458</ymax>
		</bndbox>
	</object>
</annotation>
